LICENSE
MANIFEST.in
README.md
setup.py
mezzanine_file_collections/__init__.py
mezzanine_file_collections/admin.py
mezzanine_file_collections/models.py
mezzanine_file_collections/tests.py
mezzanine_file_collections/views.py
mezzanine_file_collections.egg-info/PKG-INFO
mezzanine_file_collections.egg-info/SOURCES.txt
mezzanine_file_collections.egg-info/dependency_links.txt
mezzanine_file_collections.egg-info/top_level.txt
mezzanine_file_collections/migrations/0001_initial.py
mezzanine_file_collections/migrations/__init__.py
mezzanine_file_collections/static/img/file_icon.png
mezzanine_file_collections/static/img/file_icon.svg
mezzanine_file_collections/templates/pages/medialibrary.html