Metadata-Version: 1.1
Name: mezzanine-file-collections
Version: 1.0.1
Summary: A simple file collection page type for Mezzanine
Home-page: https://github.com/thibault/mezzanine-file-collections
Author: Thibault Jouannic
Author-email: thibault@miximum.fr
License: WTFPL
Platform: UNKNOWN
Classifier: Environment :: Web Environment
Classifier: Framework :: Django
Classifier: Intended Audience :: Developers
Classifier: License :: OSI Approved
Classifier: Operating System :: OS Independent
Classifier: Programming Language :: Python
Classifier: Programming Language :: Python :: 2.7
Classifier: Topic :: Internet :: WWW/HTTP
Classifier: Topic :: Internet :: WWW/HTTP :: Dynamic Content
Requires: m
Requires: e
Requires: z
Requires: z
Requires: a
Requires: n
Requires: i
Requires: n
Requires: e
